LICENSE
MANIFEST.in
README.txt
Readme.md
changelog.txt
setup.py
GithubAutoRepo/__init__.py
GithubAutoRepo.egg-info/PKG-INFO
GithubAutoRepo.egg-info/SOURCES.txt
GithubAutoRepo.egg-info/dependency_links.txt
GithubAutoRepo.egg-info/requires.txt
GithubAutoRepo.egg-info/top_level.txt