Metadata-Version: 2.1
Name: GithubAutoRepo
Version: 0.0.4
Summary: Github Auto Repo Creator
Home-page: 
Author: Subham Rouniyar
Author-email: subham.rouniyar27@gmail.com
License: MIT
Keywords: githubrepository
Platform: UNKNOWN
Classifier: Development Status :: 5 - Production/Stable
Classifier: Intended Audience :: Education
Classifier: Operating System :: Microsoft :: Windows :: Windows 10
Classifier: License :: OSI Approved :: MIT License
Classifier: Programming Language :: Python :: 3
License-File: LICENSE
